primosavr2022/__init__.py
primosavr2022-0.2.dist-info/LICENSE
primosavr2022-0.2.dist-info/METADATA
primosavr2022-0.2.dist-info/WHEEL
primosavr2022-0.2.dist-info/top_level.txt
primosavr2022-0.2.dist-info/RECORD
