Metadata-Version: 2.1
Name: primosavr2022
Version: 0.2
Summary: Funcion que calcula os numeros primos
Home-page: UNKNOWN
Author: Alberto Varona
Author-email: escribeme@albertovarona.es
License: GNU GPLv3
Keywords: primos operaciones matematicas
Platform: UNKNOWN
Classifier: Development Status :: 4 - Beta
Classifier: Intended Audience :: Developers
Classifier: Topic :: Utilities
Classifier: License :: OSI Approved :: GNU General Public License v3 (GPLv3)
Classifier: Programming Language :: Python :: 3
Classifier: Operating System :: OS Independent
License-File: LICENSE
